auto_subtitle_llama/__init__.py
auto_subtitle_llama/cli.py
auto_subtitle_llama/utils.py
auto_subtitle_llama-1.0.6.dist-info/LICENSE
auto_subtitle_llama-1.0.6.dist-info/METADATA
auto_subtitle_llama-1.0.6.dist-info/WHEEL
auto_subtitle_llama-1.0.6.dist-info/entry_points.txt
auto_subtitle_llama-1.0.6.dist-info/top_level.txt
auto_subtitle_llama-1.0.6.dist-info/RECORD
